tests/test_builder.py
tokyo_sports_scraper/__init__.py
tokyo_sports_scraper/builder.py
tokyo_sports_scraper/formatter.py
tokyo_sports_scraper/model.py
tokyo_sports_scraper/scraper.py
tokyo_sports_scraper/extractors/__init__.py
tokyo_sports_scraper/extractors/race_info.py
tokyo_sports_scraper/extractors/rider_info.py
tokyo_sports_scraper/extractors/utils.py
tokyo_sports_scraper-0.1.5.dist-info/licenses/LICENSE
tokyo_sports_scraper-0.1.5.dist-info/METADATA
tokyo_sports_scraper-0.1.5.dist-info/WHEEL
tokyo_sports_scraper-0.1.5.dist-info/top_level.txt
tokyo_sports_scraper-0.1.5.dist-info/RECORD
