Metadata-Version: 2.4
Name: tokyo-sports-scraper
Version: 0.1.5
Summary: 東京スポーツのオートレース情報をスクレイピングするライブラリ
Author-email: shimomo <github@shimomo.net>
License-Expression: MIT
Requires-Python: >=3.10
License-File: LICENSE
Requires-Dist: beautifulsoup4
Requires-Dist: lxml
Requires-Dist: python-dateutil
Requires-Dist: requests
Provides-Extra: dev
Requires-Dist: pytest; extra == "dev"
Dynamic: license-file
